fastapi_client/__init__.py
fastapi_client/base_client.py
fastapi_client/base_client_test.py
fastapi_client/client.py
fastapi_client/client_test.py
fastapi_client/exceptions.py
fastapi_client-0.1.0.dist-info/LICENSE
fastapi_client-0.1.0.dist-info/METADATA
fastapi_client-0.1.0.dist-info/WHEEL
fastapi_client-0.1.0.dist-info/top_level.txt
fastapi_client-0.1.0.dist-info/RECORD
