Metadata-Version: 2.1
Name: fastapi-client
Version: 0.1.0
Summary: A client for the fastapi environment
Home-page: https://github.com/LamaAni/fastapi_client
Author: Zav Shotan
Project-URL: Source, https://github.com/LamaAni/fastapi_client
Keywords: fastapi,client,fastapi_client
License-File: LICENSE
Requires-Dist: fastapi
Requires-Dist: requests
